{"api_user_add.md":"476cb277","api_user_delete.md":"dfb45e20","api_user_list.md":"a28860d7","community_join.md":"9327a05d","community_sponsor.md":"cacadae4","community_teams.md":"319a399f","contributing_index.md":"61fe226b","database_dictionary_nation.md":"64128d6d","database_index.md":"42a0fad6","database_user_users.md":"2acc943e","api_header.md":"9dceab47","guide_support_models.md":"63ec36ca","guide_support_utilities.md":"7db354c4","index.md":"e729e5a7","home.md":"2b211a60","api_response.md":"af65471d","api_index.md":"2e5a63f0","api_models_user.md":"e59c468f","api_request.md":"08a6262c","guide_index.md":"7e1a7a5d","guide_business-flowchart.md":"cb46b771","guide_support_helpers.md":"739ad2cd"}
